PyTorch_SVGRender/__init__.py
PyTorch_SVGRender/libs/__init__.py
PyTorch_SVGRender/libs/engine/__init__.py
PyTorch_SVGRender/libs/engine/model_state.py
PyTorch_SVGRender/libs/metric/__init__.py
PyTorch_SVGRender/libs/metric/accuracy.py
PyTorch_SVGRender/libs/metric/ImageReward/ImageReward.py
PyTorch_SVGRender/libs/metric/ImageReward/ReFL.py
PyTorch_SVGRender/libs/metric/ImageReward/__init__.py
PyTorch_SVGRender/libs/metric/ImageReward/utils.py
PyTorch_SVGRender/libs/metric/ImageReward/models/AestheticScore.py
PyTorch_SVGRender/libs/metric/ImageReward/models/BLIPScore.py
PyTorch_SVGRender/libs/metric/ImageReward/models/CLIPScore.py
PyTorch_SVGRender/libs/metric/ImageReward/models/__init__.py
PyTorch_SVGRender/libs/metric/ImageReward/models/BLIP/__init__.py
PyTorch_SVGRender/libs/metric/ImageReward/models/BLIP/blip.py
PyTorch_SVGRender/libs/metric/ImageReward/models/BLIP/blip_pretrain.py
PyTorch_SVGRender/libs/metric/ImageReward/models/BLIP/med.py
PyTorch_SVGRender/libs/metric/ImageReward/models/BLIP/vit.py
PyTorch_SVGRender/libs/metric/clip_score/__init__.py
PyTorch_SVGRender/libs/metric/clip_score/openaiCLIP_loss.py
PyTorch_SVGRender/libs/metric/lpips_origin/__init__.py
PyTorch_SVGRender/libs/metric/lpips_origin/lpips.py
PyTorch_SVGRender/libs/metric/lpips_origin/pretrained_networks.py
PyTorch_SVGRender/libs/metric/lpips_origin/weights/v0.1/alex.pth
PyTorch_SVGRender/libs/metric/lpips_origin/weights/v0.1/squeeze.pth
PyTorch_SVGRender/libs/metric/lpips_origin/weights/v0.1/vgg.pth
PyTorch_SVGRender/libs/metric/piq/__init__.py
PyTorch_SVGRender/libs/metric/piq/perceptual.py
PyTorch_SVGRender/libs/metric/piq/functional/__init__.py
PyTorch_SVGRender/libs/metric/piq/functional/base.py
PyTorch_SVGRender/libs/metric/piq/functional/colour_conversion.py
PyTorch_SVGRender/libs/metric/piq/functional/filters.py
PyTorch_SVGRender/libs/metric/piq/functional/layers.py
PyTorch_SVGRender/libs/metric/piq/functional/resize.py
PyTorch_SVGRender/libs/metric/piq/utils/__init__.py
pytorch_svgrender-1.0.dist-info/licenses/LICENSE
pytorch_svgrender-1.0.dist-info/WHEEL
pytorch_svgrender-1.0.dist-info/METADATA
pytorch_svgrender-1.0.dist-info/RECORD
